validio_plotting/main.py
validio_plotting-0.3.0.dist-info/METADATA
validio_plotting-0.3.0.dist-info/WHEEL
validio_plotting-0.3.0.dist-info/entry_points.txt
validio_plotting-0.3.0.dist-info/RECORD
