Metadata-Version: 2.1
Name: validio-plotting
Version: 0.3.0
Summary: App to graph  metrics from Validio SDK
License: Apache-2.0
Author: Validio
Author-email: support@validio.io
Requires-Python: >=3.10,<4.0
Classifier: License :: OSI Approved :: Apache Software License
Classifier: Programming Language :: Python :: 3
Classifier: Programming Language :: Python :: 3.10
Classifier: Programming Language :: Python :: 3.11
Classifier: Programming Language :: Python :: 3.12
Requires-Dist: plotext (>=5.2.8,<6.0.0)
Requires-Dist: prompt-toolkit (>=3.0.43,<4.0.0)
Requires-Dist: typer (>=0.8.0,<0.9.0)
Requires-Dist: validio-cli (==0.26.0)
Requires-Dist: validio-sdk (==0.26.0)
